dtd_obsidian_tools-0.1.2.dist-info/licenses/LICENSE
obsidian/__init__.py
obsidian/colorclass_processor.py
obsidian/graph.py
obsidian/parser.py
dtd_obsidian_tools-0.1.2.dist-info/METADATA
dtd_obsidian_tools-0.1.2.dist-info/WHEEL
dtd_obsidian_tools-0.1.2.dist-info/entry_points.txt
dtd_obsidian_tools-0.1.2.dist-info/top_level.txt
dtd_obsidian_tools-0.1.2.dist-info/RECORD
