Metadata-Version: 2.4
Name: dtd-obsidian-tools
Version: 0.1.2
Summary: Tools for working with Obsidian vaults, including community detection and graph analysis
Author-email: Your Name <your.email@example.com>
Maintainer-email: Your Name <your.email@example.com>
License: MIT License
Project-URL: Homepage, https://github.com/yourusername/dtd-obsidian-tools
Project-URL: Documentation, https://github.com/yourusername/dtd-obsidian-tools#readme
Project-URL: Repository, https://github.com/yourusername/dtd-obsidian-tools
Project-URL: Bug Tracker, https://github.com/yourusername/dtd-obsidian-tools/issues
Keywords: obsidian,knowledge-graph,community-detection,networkx,markdown
Classifier: Development Status :: 4 - Beta
Classifier: Intended Audience :: End Users/Desktop
Classifier: Intended Audience :: Developers
Classifier: License :: OSI Approved :: MIT License
Classifier: Operating System :: OS Independent
Classifier: Programming Language :: Python :: 3
Classifier: Programming Language :: Python :: 3.10
Classifier: Programming Language :: Python :: 3.11
Classifier: Programming Language :: Python :: 3.12
Classifier: Topic :: Text Processing :: Markup
Classifier: Topic :: Scientific/Engineering :: Information Analysis
Classifier: Topic :: Office/Business :: Groupware
Requires-Python: >=3.10
License-File: LICENSE
Requires-Dist: networkx>=3.0
Requires-Dist: loguru>=0.7.0
Requires-Dist: fire>=0.5.0
Requires-Dist: omegaconf>=2.3.0
Requires-Dist: pyyaml>=6.0
Requires-Dist: python-frontmatter>=1.0.0
Requires-Dist: seaborn>=0.11.0
Provides-Extra: dev
Requires-Dist: pytest>=7.0; extra == "dev"
Requires-Dist: pytest-cov>=4.0; extra == "dev"
Requires-Dist: black>=23.0; extra == "dev"
Requires-Dist: isort>=5.12; extra == "dev"
Requires-Dist: flake8>=6.0; extra == "dev"
Requires-Dist: mypy>=1.0; extra == "dev"
Requires-Dist: pre-commit>=3.0; extra == "dev"
Provides-Extra: docs
Requires-Dist: mkdocs>=1.4; extra == "docs"
Requires-Dist: mkdocs-material>=9.0; extra == "docs"
Requires-Dist: mkdocstrings[python]>=0.20; extra == "docs"
Dynamic: license-file
